setup.py
cn/__init__.py
cn/ruitool/__init__.py
cn/ruitool/core/ArrUtil.py
cn/ruitool/core/__init__.py
ruitools.egg-info/PKG-INFO
ruitools.egg-info/SOURCES.txt
ruitools.egg-info/dependency_links.txt
ruitools.egg-info/top_level.txt